Исчисление разных классов общества с целью обличения их ведется с точки зрения значения их в религиозно-нравственной жизни. Посему сначала разбираются пророки и священники, а затем князья. LXX, а вслед за ними и большинство новейших толкователей, предполагают в этом стихе речь не о пророках, а о князьях (более знатных, чем в ст. 27): <i>невийега</i> LXX очевидно читали <i>несийега</i>. Основания для такого чтения: <b>1)</b> естественнее было поставить князей на первом месте (мы видели, почему пророков можно было поставить на первом месте); <b>2)</b> о пророках речь в ст. 28 и 30 (но там речь о них по особым обстоятельствам - <i>см.</i> 28 ст.); <b>3)</b> рыкающий, жадный к добыче царь зверей, как и в <a href='B:330 19:8'>Иез 19:8</a>, превосходный образ для жадных князей из царствовавшего дома (но тогда 27 ст. повторял бы 25). - <i>“Заговор пророков”</i>. Ложные пророки вступили между собою в соглашение на счет того, чтобы всегда возвещать народу счастливое будущее, и этим восстановляли его против тех, которые предсказывали противоположное. Отсюда можно заключить, что ложные пророки действовали не в одиночку, а составляли корпорацию, ставшую могущественною через свое единство, и весьма заботились о том, чтобы не противоречить между собою в ложных предсказаниях. Но LXX читают евр. “кешер” - “заговор”, как “ашер”, “который”: “его же (т. е. Иерусалима) старейшины”. <i>“Как лев&#133;”</i> Сравнение указывает на обирание пророками адептов. - <i>“Съедают души”</i>. Обирают, или губят невинных, которые им противятся. - <i>“Умножают число вдов”</i>. Становятся благодаря своим речам причиною смерти для многих, <i>напр.</i> возбуждая к войне с халдеями.