О положении филистимских городов Азота евр. <i>Ашдод</i> (Onomast. 36) и Гефа, евр. <i>Гат </i>(Onomast. 301) <i>см.</i> примеч. к <a href='C:@60 11:22'>Нав 11:22</a> в Толков. Библии т. II. Иавнея (Иавнеил, Иамния), <i>слав.</i> Иавнир или Иамния (LXX <b>&#923;εβνα, &#921;αβνηρ, &#921;αμνια</b>), - тоже филистимский город, составлявший предел колена Иудина (<a href='B:60 15:11'>Нав 15:11</a>, Onomast. 533), недалеко от Иоппии (1Мак 10:69,75</a>), в 240 стадиях от Иерусалима, в 12 милях от Диосполя (Лидда) и в 20 от Аскалона (по разрушении Иерусалима, здесь заседал Синедрион; в христианскую эпоху тут была епископская кафедра). Это покорение Озией филистимлян, снова освободившихся от иудейского господства при Ахазе (<a href='B:140 28:18'>2Пар 28:18</a>), - событие, совершенно не упомянутое в кн. Царств, по вероятному предположению некоторых экзегетов, имеется в виду у пророка Исайи <a href='B:290 14:28'>Ис 14:28</a>.