{"chapter":{"1":{"verse":1,"text":"«Εις τον πρώτον μουσικόν. Ψαλμός του Δαβίδ.» Άκουσον, Θεέ, της φωνής μου εν τη δεήσει μου· από του φόβου του εχθρού φύλαξον την ζωήν μου."},"2":{"verse":2,"text":"Σκέπασόν με από συμβουλίου πονηρών, από φρυάγματος εργαζομένων ανομίαν·"},"3":{"verse":3,"text":"οίτινες ακονώσιν ως ρομφαίαν την γλώσσαν αυτών· ετοιμάζουσιν ως βέλη λόγους πικρούς,"},"4":{"verse":4,"text":"διά να τοξεύωσι κρυφίως τον άμεμπτον· εξαίφνης τοξεύουσιν αυτόν και δεν φοβούνται."},"5":{"verse":5,"text":"Στερεούνται επί πονηρού πράγματος· μελετώσι να κρύπτωσι παγίδας, λέγοντες, Τις θέλει ιδεί αυτούς;"},"6":{"verse":6,"text":"Ανιχνεύουσιν ανομίας· απέκαμον ανιχνεύοντες επιμελώς· εκάστου δε τα εντός και η καρδία είναι βυθός."},"7":{"verse":7,"text":"Αλλ' ο Θεός θέλει τοξεύσει αυτούς· από αιφνιδίου βέλους θέλουσιν είσθαι αι πληγαί αυτών."},"8":{"verse":8,"text":"Και οι λόγοι της γλώσσης αυτών θέλουσι πέσει επ' αυτού· θέλουσι φεύγει πάντες οι βλέποντες αυτούς."},"9":{"verse":9,"text":"Και θέλει φοβηθή πας άνθρωπος, και θέλουσι διηγηθή το έργον του Θεού και εννοήσει τας εργασίας αυτού."},"10":{"verse":10,"text":"Ο δίκαιος θέλει ευφρανθή εις τον Κύριον και θέλει ελπίζει επ' αυτόν· και θέλουσι καυχάσθαι πάντες οι ευθείς την καρδίαν."}},"meta":{"connection":"GreVamvas","book_number":230,"chapter_number":64,"previous_chapter":{"connection":"GreVamvas","book_number":230,"chapter":63},"next_chapter":{"connection":"GreVamvas","book_number":230,"chapter":65}}}