Евреев ожидает страшное поражение, несмотря на их союз с Египтом! Однако Всевышний, как Бог правды, снова наградит Иуду Своими милостями после того, как он исправится и искупит вину свою пред Богом своими страданиями. Господь пошлет тогда Своему народу и плодородие как необходимое условие спокойной жизни.<p/><i>Оставаясь на месте</i>. Евреи, очевидно, замышляли в то время сделать набег на области, принадлежавшие ассирийцам.<p/><i>Убежим, ускачем</i> - возможно правильнее: "устремимся, поскачем". Евреи рассчитывали на коней и колесницы, какие они могли получить от египтян.<p/><i>За то и побежите</i>, т. е. кони и колесницы разве только помогут вам убежать от врагов!<p/><i>Как веха</i> - по-евр.: как кедр или как мачта; сделанная из кедра. Здесь пророк указывает на то, что остаток Израиля будет очень мал - похож на одиноко стоящую мачту.