Они обращались, но не к Всевышнему</i>, точнее с евр. но не вверх, lo al. По-видимому, LXX сделали в выражении перестановку и читали al lo, <b>εις ουδεν</b>, отсюда <i>слав.</i> <i>"совратишася нивочтоже"</i>. Стали как неверный (remijah) лук: смысл сравнения тот, что как неверный лук не попадает в цель, так и Израиль уклонился от своего назначения - чтить Иегову. Вместо чтения <i>слав.</i> текста <i>"яко лук напряжен"</i>, <b>ως το&#958;ονεντεταμενον</b> возникшего, может быть, из замены мазоретск. remijah, словом romeh (стреляющий), многие кодексы имеют. <b>ως το&#958;ον ου τεταμενον</b>, "как лук не натянутый". - <i>Падут от меча князья их за дерзость языка своего</i>: дерзость языка выразилась во лжи на Иегову (<i>ст.</i> <a href='B:350 7:13'>13</a>), в поношении Его всемогущества. Князья Израильские надеются на Египет. Но эта надежда тщетна, они падут, и это падение будет предметом посмеяния в Египте.