Продолжая поучать христиан безропотному и терпеливому несению злостраданий, Апостол для подкрепления своих наставлений ссылается на пример ветхозаветных пророков, которые безропотно переносили великие страдания за истину проповедуемого ими слова Божия. Рядом с пророками в качестве великого образца терпения страданий Апостол называет (<i>ст.</i> <a href='B:660 5:11'>11</a>) праведного Иова, в истории которого он одновременно отмечает благоприятное окончание страданий праведника, благословенного Богом за терпение великими благами. История Иова, которую Апостол представляет хорошо известною читателям, таким образом, в двух отношениях особенно назидательна для страждущих христиан; и по исключительному терпению Иова, и по конечному его оправданию Господом. <b>&#932;ο τελος &#922;υριου</b> - не смерть и прославление Господа, как думали некоторые толкователи (блаж. Августин, Лянге), а именно - дарованная Господом награда за терпение Иова. Выражением <i>«вы слышали о терпении Иова»</i> Апостол, быть может, намекает на синагогальные чтения из книги Иова, знакомившие иудеев с великим подвигом терпения этого праведника. Место <a href='B:660 5:11'>Иак 5:11</a> весьма важно, как свидетельство об историческом существовании Иова.<p/>В конце ст. 11 Апостол к истории прославления делает замечание: <i>«ибо Господь весьма милосерд и сострадателен»</i>, что должно исполнить читателей надеждою, что их терпение скорбей, по милосердию Господа, будет вознаграждено.