Здесь дается общая характеристика дальнейшего развития Иоанна. Младенец <i>«возрастал»</i> телесно <i>«и укреплялся духом»</i>, т. е. приобретал тот твердый характер, какой он обнаружил впоследствии.<p/><i>«В пустынях»</i>. Здесь по преимуществу разумеется пустыня иудейская (<i>см.</i> <a href='B:470 3:1'>Мф 3:1</a>). Когда он удалился в пустыню? Церковное предание сообщает, что он жил в пустыне с самого раннего детства. Но у кого? Некоторые толкователи полагают, что Иоанн получил воспитание у ессеев, которые имели своим местопребыванием также пустыню. Но такое предположение неосновательно. Ессеи не верили в пришествие Мессии, а Иоанн себя называл предтечей Мессии. Те жили вдали от людей, а Иоанн идет на проповедь людям. Притом и сам контекст речи говорит против этого предположения: Иоанн идет в пустыню, живет там в уединении для того, чтобы подготовиться к своему служению - зачем же ему вступать в ессейское общество, которое было очень велико по числу своих членов? Не лучше ли бы было ему остаться в своем собственном городе?<p/><i>«До дня явления...»</i> т. е. до того времени, когда голос Божий призвал его на проповедническое служение Предтечи (<a href='B:490 3:2-6'>Лк 3:2-6</a>).