Узнав от сыновей о пророке Иудейском, его предсказании и действиях в Вефиле, Вефильский пророк отправляется вслед за ним и находит его сидящим под дубом (LXX: <b>υπο δρυν</b>), - евр. <i>эла</i> - собственно; теревинф (Vulg: terebinthus) - "похожее на дуб, дерево с вечнозелеными листьями и гроздеобразными плодами, достигает значительной высоты, почему и служит для топографических определений: <a href='B:10 35:4'>Быт 35:4</a>; <a href='B:70 6:11,19'>Суд 6:11,19</a>; <a href='B:90 17:2,9'>1Цар 17:2,9</a> (Гезениус). Здесь говорится об известном в Вефиле теревинфе (<i>га-эла</i> - с членом), может быть, тождественным с тем, под которым погребена была кормилица Ревекки, Девора (<a href='B:10 35:8'>Быт 35:8</a>).