Вместе с падением Вавилона в представлении пророка Исаии соединяется возвращение Израиля из плена в свою страну. Язычники сами вернут Израиля домой и Израиль в свою очередь будет господствовать над ними.<p/><i>Близко время его и не замедлят дни его.</i> В еврейской Библии эти слова отнесены к 22-му стиху 13-й главы.<p/><i>Его,</i> т. е. Вавилона.<p/><i>Ибо помилует…</i> Как основание к разрушению Вавилона здесь указывается намерение Господа освободить свой народ, который, очевидно, представляется пророку живущим в вавилонском плену. Значит, по представлению пророка, освобождение из вавилонского плена Израилю возможно было получить только в случае разрушения Вавилонской монархии. В 17-м стихе пророк, как бы в подтверждение этой мысли, говорит, что царь вавилонский никогда не отпускал домой своих пленников.<p/><i>Присоединятся к ним иноземцы.</i> Иноземцы или иноплеменники, пришельцы всегда жили среди евреев (<a href='B:20 12:19,38'>Исх 12:19,38</a>; <a href='B:110 9:20'>3Цар 9:20</a>; <a href='B:330 14:7'>Иез 14:7</a>), а тогда, когда евреи снова будут в милости у Бога, их число естественно будет умножаться.