Пророчества против Тира есть еще у <a href='B:370 1:9,10'>Ам 1:9,10</a>; <a href='B:360 3:4'>Иоил 3:4</a>; <a href='B:290 23:1'>Ис 23:1</a>; <a href='B:300 25:22'>Иер 25:22</a>; <a href='B:300 47:4'>Иер 47:4</a>; <a href='B:450 9:2-4'>Зах 9:2-4</a>. <i>Тир</i> по евр. “Цор” - “скала”. LXX, везде передавая это слово “Тир” <b>&#932;υρος</b>, здесь почему-то предпочитают транскрипцию <b>&#931;ορ</b>, <i>слав.</i> <i>“Сор”</i>: может быть, они хотят этим указать на Тир островной, заменивший взятый еще Салманассаром и впоследствии разрушенный Александром Тир континентальный, от которого первый находился в 1 200 футах; пророк, действительно, имеет в виду, кажется, более островной Тир: ст. 5, 14; <a href='B:330 27:4,25,25'>Иез 27:4,25</a>. - <i>“А! а!”</i> - <i>см.</i> объяснение <a href='B:330 25:3'>Иез 25:3</a>. - <i>“Вратами народов”</i> Иерусалим являлся для Тира, поскольку торговые караваны, идущие с юга, из богатого <i>напр.</i> Египта, должны были проходить через Иудею и едва ли беспошлинно или по крайней мере безвыгодно для Иерусалима и без ущерба для Тира, почему последний и рад уничтожению этих ворот. LXX: <i>“погибоша языцы”</i>, т. е. жившие на счет Иерусалима. <i>“Наполнюсь; он опустошен”</i>. Иерусалим не будет соперником в торговле для Тира. Слав.: <i>“иже бе исполненный опусте”</i>.