<i>За то</i>. Хотя эти ужасные жертвы были отменены царем Иосией и не возобновлялись при Иоакиме (это видно из того, что поражение иудеев при Иоакиме приписывается в кн. Царств преступлениям <i>только</i> Манассии; <a href='B:120 24:3'>4Цар 24:3</a> <i>ср.</i> <a href='B:300 21:11'>Иер 21:11</a> и 23, 26), тем не менее со времени отмены их прошло только 18 лет (до 5-го г. Иоакима), и современники Манассии еще не искупили своего участия в этих беззаконных жертвах никакими страданиями. Теперь им предстоит понести наказание. — <i>Долиною убийства</i>. Сюда, в долину сынов Гинномовых, будет свезено столько трупов убитых Иерусалимлян для погребения, что ее можно будет переименовать в <i>долину убийства</i> или <i>убитых</i>.