Колосские еретики считали Христа только одним из эонов - выразителей Божества. В противовес им, Ап. говорит, что во Христе обитает вся полнота Божества <SMALL>[Божество по-гречески обозначается двумя терминами: <b>θεοτης</b> и <b>θειοτης</b>.<p/>Первое слово происходит от термина <b>θεος</b> и употребляется для обозначения божеского существа, а второе, происходящее от прилаг. <b>θειος</b> = божественный - употребляется для обозначения свойств Божества (<i>ср.</i> <a href='B:520 1:19-20'>Рим 1:19-20</a>). Ясно, что Ап. здесь хочет дать понять своим читателям, что в Христе имеются не только божественные свойства (<b>θειοτης</b>), но пребывает и Сам Бог (<b>&#920;εος</b>): Он - по существу Бог]</SMALL> и притом <i>телесно</i> или в теле (<b>σωματικως</b> - равняется выражению <b>εν σωματι</b>), так что мы можем наблюдать ее: Ап. конечно хочет сказать, что Бога мы можем видеть в воплотившемся Сыне Божием, Иисусе Христе (<i>ср.</i> <a href='B:580 1:19'>Кол 1:19</a>).