<i>“И повел”</i>, не: “привел”, как в ст. 17, потому что здесь больше и довольно значительное расстояние. Южные врата были во всем подобны восточным и северным, но измерение их описывается не так, как северных (хороший писатель не любит повторяться), а с незначительными отклонениями. Так, прежде всего, почему-то не говорится о столь важной части ворот, как боковые комнаты (LXX ставят на первом месте опускаемое евр. т.: <i>“фе”</i>), а измерение начинается прямо со <i>столбов</i> (должно быть между боковыми комнатами), после которых сразу называются упоминаемые в 22 ст. (<i>см.</i> там) <i>еламав</i>, LXX <b>τα ελαμμων</b>, <i>слав.</i> <i>“еламы”</i>, рус <i>“выступы”</i>.