Не допускает никакого выкупа «все заклятое, cherem (слав. «обет»), что под заклятием отдает человек Иегове из своей собственности, человека ли, скотину ли, поле ли…» Заклятое — херем, во-первых, есть «qodesch qodaschim lajhovah, великая святыня Господня» и, как такое, никоим образом, не может быть предметом владения или пользования человека (<i>ст.</i> <a href='B:30 27:28'>28</a>); во-вторых, заклятое — человек или скотина — не может остаться в живых, а должно быть предано смерти (<i>ст.</i> <a href='B:30 27:29'>29</a>). Чтобы обречение на смерть человека имело моральное основание и религиозное освящение, оно у народа Божия могло простираться на лица и народы, враждующие против Царства Божия (<i>ср.</i> <a href='B:40 21:2'>Чис 21:2</a>; <a href='B:50 12:16'>Втор 12:16</a>; <a href='B:60 6:17'>Нав 6:17</a>; <a href='B:60 7:12'>Нав 7:12</a>; <a href='B:90 15:18'>1Цар 15:18–19</a>; <a href='B:110 20:42'>3Цар 20:42</a>).