Потом представляет главное утешение, которое он предлагает и прежде, и после - Христа... <i>взирающе</i>, говорит, т е. чтобы нам научиться подвигам, будем взирать на Христа (Злат.). - <i>Вместо предлежавшей Ему радости претерпел крест...</i>, т е. Он мог бы и не страдать, если бы захотел, потому что Он <i>беззакония не сотвори, ниже обретеся лесть во устех Его</i> (<a href='B:290 53:9'>Ис 53:9</a>; <a href='B:500 14:30'>Ин 14:30</a>; <a href='B:500 10:18'>Ин 10:18</a>). Если же Он, не имея никакой нужды быть распятым, распялся для нас, то не тем ли более справедливо нам переносить все мужественно? (Злат.). - <i>«Пренебрегши посрамление...»</i> "Пусть Он умер: но для чего поносной смертью? Не для чего иного, как для того, чтобы изучить нас ставить ни во что славу человеческую" (Злат.). - <i>«Возсел одесную Престола Божия...»</i> Замечаешь победную награду? То же говорит Павел и в другом послании (<a href='B:570 2:9-10'>Флп 2:9-10</a>). Это говорит он о Христе по плоти" (Злат.).