Один евангелист Лука делает замечание о женщинах, которые во время проповеднических путешествий Христа с 12 апостолами служили Ему своим имением.<p/><i>«Мария Магдалина»</i> (<i>см.</i> <a href='B:470 27:56'>Мф 27:56</a>).<p/><i>«Из которой вышли семь бесов»</i>. Это выражение обозначает чрезвычайную силу одержимости бесами: «семь» на языке Священного Писания есть символ полноты (<i>ср.</i> <a href='B:470 12:45'>Мф 12:45</a>). Согласно И. Вейса, здесь указывается на то, что Мария семь раз в течение своей жизни подвергалась возвращению бесноватости. Что касается довольно распространенного рационалистического взгляда, будто бы Мария была просто крайне распущенная в нравственном отношении женщина, что и обозначил будто бы евангелист своим замечанием, то против такого понимания говорит употребленный и о Мариитермин «исцеленная» (<b>τεθεραπευμ&#8051;ναι</b>), который означает чудесное исцеление от действительной, а не мнимой болезни беснования.<p/><i>«Домоправителя Иродова»</i>, т. е. по-нашему гофмейстера при дворе Ирода (вероятно, Антипы). Должность эта была видная (<i>ср.</i> <a href='B:470 20:8'>Мф 20:8</a>).<p/>Жены эти служили Христу до самой Его смерти на кресте (<i>см.</i> <a href='B:490 24:10'>Лк 24:10</a>).<p/><i>«Сусанна»</i> - личность неизвестная.