Ходившему по земле для наблюдения злому духу и задается теперь естественный вопрос: обратил ли он внимание на исключительное благочестие Иова (<i>ст.</i> 8 <i>ср.</i> <a href='B:10 6:9'>Быт 6:9</a>; <a href='B:10 7:1'>Быт 7:1</a>), а в не замедлившем последовать ответе сатаны сказывается его полная противоположность Господу. По словам сатаны, в благочестии Иова нет ничего выдающегося, заслуживающего похвалы, как то делает Бог, - оно корыстно. Иов чтит Господа лишь потому, что это для него выгодно: в награду за благочестие он избавляется Богом от всяких бедствий (<i>"кругом оградил", ср.</i> <a href='B:290 5:5'>Ис 5:5</a>) и пользуется успехом во всех своих делах. Истинный, т. е. корыстный, характер благочестия Иова скажется в том случае, если Господь "прострет на него свою руку" (<i>ст.</i> <a href='B:220 1:11'>11</a>), - поразит бедствиями (<a href='B:20 3:20'>Исх 3:20</a>; <a href='B:20 9:15'>Исх 9:15</a>; <a href='B:230 31:4'>Пс 31:4</a>; <a href='B:230 37:3'>Пс 37:3</a>). При таких обстоятельствах не будет побуждения к благочестию. Оно исчезнет, мало того, сменится проклятием "в лице", т. е. проклятием дерзким, беззастенчивым (<a href='B:290 65:3'>Ис 65:3</a>). Синодальное чтение: <i>"благословит ли он тебя?"</i> передает из целой еврейской фразы: "им-ло ал-панейка йебарекека" только последнее слово. "Йебарекека" - глагольная форма от "барак", означающего и "благословлять", и "проклинать", "хулить" (<a href='B:220 1:5'>Иов 1:5</a>; <a href='B:220 2:9'>Иов 2:9</a>; <a href='B:110 21:10,13'>3Цар 21:10,13</a>), причем последнее значение всеми усвояется данному глаголу и в настоящем случае. Ближе к подлиннику славянское чтение: <i>"аще не в лице тя благословит"</i>.