<i>Ибо</i>. Соединительный предлог показывает, что ироническая речь Апостола еще продолжается. - <i>Я думаю</i> - правильнее: "кажется" - <i>Что нам...</i> Правильнее: "что Бог нас, апостолов, выставил как последних, как бы осужденных на смерть". Ап. дивится, как это коринфяне могли вообразить, что Апостолы должны после них, <i>последними</i> войти в царство Христово, которое Он обещал любящим Его. Ужели, в самом деле, Апостолы должны стоять всегда в положении гладиаторов, приговоренных к смерти, тогда как их духовные чада будут наслаждаться покоем? - <i>Мы сделались позорищем</i>, т. е. зрелищем, которое собираются смотреть люди разного положения. - <i>Для мира</i>. Это слово обозначает совокупность всех разумных существ. - <i>Для Ангелов</i> - как добрых, так и злых (<i>ср.</i> <a href='B:560 3:10'>Еф 3:10</a>).