Из двух стихов - 20 и 21, в первом указывается частое, хотя и не нормальное с нравственной точки зрения, явление - дружба лишь по видам корысти, - а во втором проводится моральное воззрение на этот пункт. Далее следуют сентенции: о гибельности злоумышления против ближнего и о благотворности доброжелательства (<i>ст.</i> <a href='B:240 14:22'>22</a>), о пользе труда и о вреде празднослова (<i>ст.</i> <a href='B:240 14:23'>23</a>), о богатстве, как уделе мудрых, и скудости, постигающей безумного (<i>ст.</i> <a href='B:240 14:24'>24</a>), о спасительности истинного свидетельства и пагубности лжесвидетельства (<i>ст.</i> <a href='B:240 14:25'>25</a>); наконец, в связи с последним, а вместе с содержанием целого отдела, говорится о страхе Божьем, как источнике всякого блага жизни и самой жизни (<i>ст.</i> 26-27).